{
  "url": "http://127.0.0.1:5174/?filter=nav%3Aplus-navigation-tabs",
  "title": "UI 용어 사전",
  "severe": [],
  "overlayText": 0,
  "tablistCount": 18,
  "tabCount": 72,
  "tabpanelCount": 9,
  "ariaSelectedTrueCount": 18,
  "ariaControlsCount": 72,
  "firstPanelLabelledBy": "tabs-underline-account-tabs-company-desktop-tab",
  "billingFeedback": 1,
  "darkButtonCount": 9,
  "darkSurfaceCount": 3,
  "bodyOverflowX": 0,
  "mobileOverflowX": 0,
  "mobileExpandedButtons": 0,
  "mobileCollapsedButtons": 9,
  "mobileMobileTablistCount": 18,
  "mobileMobileCompanyFeedback": 1,
  "mobileMobileSelectedCompany": 2,
  "timestamp": "2026-07-03T14:56:48.821Z",
  "darkPressedTrueCount": 0,
  "darkAppliedTextCount": 22,
  "mobileExpandedBeforeSelection": 1,
  "mobileVisibleCompanyOptions": 9,
  "mobileExpandedAfterSelection": 0,
  "supplementalTimestamp": "2026-07-03T14:57:15.798Z",
  "visibleSelectedTabsAfterBilling": [
    "Billing",
    "♣Team Members",
    "Team Members",
    "Team Members",
    "Team Members",
    "Team Members",
    "Team Members",
    "Team Members52",
    "Team Members"
  ],
  "firstPanelTextAfterBilling": "Billing\n\nActive tab content updates in place while the tab bar keeps its layout stable.\n\nBilling tab opened",
  "firstPanelLabelledByAfterBilling": "tabs-underline-account-tabs-billing-desktop-tab",
  "fixedClickTimestamp": "2026-07-03T14:57:40.146Z"
}